CoRE_MOF/__init__.py
CoRE_MOF/load.py
CoRE_MOF/data/2014.csv
CoRE_MOF/data/2014.tar.xz
CoRE_MOF/data/2019-ASR.csv
CoRE_MOF/data/2019-ASR.tar.xz
CoRE_MOF/data/2019-FSR.csv
CoRE_MOF/data/2019-FSR.tar.xz
core_mof-2019.1.dist-info/METADATA
core_mof-2019.1.dist-info/WHEEL
core_mof-2019.1.dist-info/licenses/LICENSE
core_mof-2019.1.dist-info/RECORD
